githubcifun/__init__.py
githubcifun/content_test.py
githubcifun-0.1.5.dist-info/LICENSE
githubcifun-0.1.5.dist-info/METADATA
githubcifun-0.1.5.dist-info/WHEEL
githubcifun-0.1.5.dist-info/RECORD
