Metadata-Version: 2.1
Name: githubcifun
Version: 0.1.5
Summary: 
Author: Konstantin Wrede
Author-email: konstantin.wrede@eas.iis.fraunhofer.de
Requires-Python: >=3.10,<4.0
Classifier: Programming Language :: Python :: 3
Classifier: Programming Language :: Python :: 3.10
Classifier: Programming Language :: Python :: 3.11
Classifier: Programming Language :: Python :: 3.12
Requires-Dist: fmpy (>=0.3.20,<0.4.0)
Requires-Dist: gymnasium (>=0.29.1,<0.30.0)
Requires-Dist: matplotlib (>=3.8.3,<4.0.0)
Requires-Dist: numpy (>=1.26.4,<2.0.0)
Requires-Dist: pytest (>=8.1.1,<9.0.0)
Requires-Dist: pytest-cov (>=5.0.0,<6.0.0)
